test/__init__.py
test/main.py
task_cli_nemkov-0.1.0.dist-info/METADATA
task_cli_nemkov-0.1.0.dist-info/WHEEL
task_cli_nemkov-0.1.0.dist-info/RECORD
