Metadata-Version: 2.3
Name: task-cli-nemkov
Version: 0.1.0
Summary: Task managment via CLI
Author: roBoot-LDT
Author-email: maksim.nemkov.ldt@gmail.com
Requires-Python: >=3.13
Classifier: Programming Language :: Python :: 3
Classifier: Programming Language :: Python :: 3.13
